qrguide/__init__.py
qrguide/analysis_fn.py
qrguide/transformation.py
qrguide/unet2.py
qrguide/version.py
qrguide/utils/Model_weights.pkl
qrguide/utils/__init__.py
qrguide/utils/coding_XY.py
qrguide/utils/model_prereq.pkl
qrguide-0.0.3.dist-info/LICENSE
qrguide-0.0.3.dist-info/METADATA
qrguide-0.0.3.dist-info/WHEEL
qrguide-0.0.3.dist-info/top_level.txt
qrguide-0.0.3.dist-info/RECORD
