Metadata-Version: 2.1
Name: qrguide
Version: 0.0.3
Summary: QRguide: QR code representation of guide RNA for predicting CRISPR editings
Home-page: https://github.com/StatBiomed/QRguide
Author: ['QRguide Team']
Author-email: 
License: Apache-2.0
Keywords: CRISPR editing prediction,multivariate regression,sequence model
License-File: LICENSE
Requires-Dist: numpy >=1.9.0
Requires-Dist: scipy >=1.4.0
Requires-Dist: matplotlib
Requires-Dist: statsmodels >=0.13
Provides-Extra: docs
Requires-Dist: sphinx-bootstrap-theme ; extra == 'docs'
